{
"meta":{"test_sets":[],"test_metrics":[],"learn_metrics":[{"best_value":"Min","name":"RMSE"}],"launch_mode":"Train","parameters":"","iteration_count":100,"learn_sets":["learn"],"name":"experiment"},
"iterations":[
{"learn":[14.005006],"iteration":0,"passed_time":0.001420544281,"remaining_time":0.1406338838},
{"learn":[13.14441192],"iteration":1,"passed_time":0.003378530639,"remaining_time":0.1655480013},
{"learn":[12.34258257],"iteration":2,"passed_time":0.008703448913,"remaining_time":0.2814115149},
{"learn":[11.64527793],"iteration":3,"passed_time":0.01035243938,"remaining_time":0.2484585452},
{"learn":[11.02766183],"iteration":4,"passed_time":0.01184320375,"remaining_time":0.2250208713},
{"learn":[10.43485794],"iteration":5,"passed_time":0.01403565637,"remaining_time":0.2198919498},
{"learn":[9.890641275],"iteration":6,"passed_time":0.01526507365,"remaining_time":0.2028074071},
{"learn":[9.492161212],"iteration":7,"passed_time":0.01638598963,"remaining_time":0.1884388808},
{"learn":[9.105082953],"iteration":8,"passed_time":0.01854262249,"remaining_time":0.1874865162},
{"learn":[8.674157135],"iteration":9,"passed_time":0.01994975994,"remaining_time":0.1795478395},
{"learn":[8.341743544],"iteration":10,"passed_time":0.021321679,"remaining_time":0.1725117665},
{"learn":[8.049372916],"iteration":11,"passed_time":0.02389768832,"remaining_time":0.1752497143},
{"learn":[7.757318612],"iteration":12,"passed_time":0.02545327246,"remaining_time":0.1703411311},
{"learn":[7.522206899],"iteration":13,"passed_time":0.02945767263,"remaining_time":0.1809542747},
{"learn":[7.297756655],"iteration":14,"passed_time":0.03073471232,"remaining_time":0.1741633698},
{"learn":[7.088359431],"iteration":15,"passed_time":0.03320089605,"remaining_time":0.1743047042},
{"learn":[6.882113791],"iteration":16,"passed_time":0.03471174626,"remaining_time":0.1694749964},
{"learn":[6.704728832],"iteration":17,"passed_time":0.03690179101,"remaining_time":0.168108159},
{"learn":[6.563881962],"iteration":18,"passed_time":0.0392686035,"remaining_time":0.167408257},
{"learn":[6.418790279],"iteration":19,"passed_time":0.04051738051,"remaining_time":0.162069522},
{"learn":[6.315756953],"iteration":20,"passed_time":0.04170038132,"remaining_time":0.156872863},
{"learn":[6.210157751],"iteration":21,"passed_time":0.04296857163,"remaining_time":0.1523431176},
{"learn":[6.115058449],"iteration":22,"passed_time":0.04420477509,"remaining_time":0.1479898992},
{"learn":[6.014819884],"iteration":23,"passed_time":0.04563412957,"remaining_time":0.144508077},
{"learn":[5.93117229],"iteration":24,"passed_time":0.04748880861,"remaining_time":0.1424664258},
{"learn":[5.844857622],"iteration":25,"passed_time":0.04992768688,"remaining_time":0.1421018781},
{"learn":[5.771145213],"iteration":26,"passed_time":0.0582307576,"remaining_time":0.157438715},
{"learn":[5.704018229],"iteration":27,"passed_time":0.06002958701,"remaining_time":0.1543617952},
{"learn":[5.665806474],"iteration":28,"passed_time":0.06157861608,"remaining_time":0.1507614394},
{"learn":[5.616500369],"iteration":29,"passed_time":0.06316542736,"remaining_time":0.1473859972},
{"learn":[5.558023666],"iteration":30,"passed_time":0.06455744186,"remaining_time":0.1436923706},
{"learn":[5.510080976],"iteration":31,"passed_time":0.06601630894,"remaining_time":0.1402846565},
{"learn":[5.468747792],"iteration":32,"passed_time":0.0676202624,"remaining_time":0.1372896237},
{"learn":[5.429275534],"iteration":33,"passed_time":0.07261815255,"remaining_time":0.1409646491},
{"learn":[5.402117324],"iteration":34,"passed_time":0.07501288307,"remaining_time":0.13930964},
{"learn":[5.367635151],"iteration":35,"passed_time":0.07641534313,"remaining_time":0.1358494989},
{"learn":[5.345181232],"iteration":36,"passed_time":0.07771504687,"remaining_time":0.1323256204},
{"learn":[5.319151269],"iteration":37,"passed_time":0.08121941932,"remaining_time":0.1325158947},
{"learn":[5.296134146],"iteration":38,"passed_time":0.08555724034,"remaining_time":0.133820299},
{"learn":[5.269629003],"iteration":39,"passed_time":0.08690098068,"remaining_time":0.130351471},
{"learn":[5.251147059],"iteration":40,"passed_time":0.08916747431,"remaining_time":0.1283141704},
{"learn":[5.248003302],"iteration":41,"passed_time":0.08975878839,"remaining_time":0.1239526125},
{"learn":[5.232376509],"iteration":42,"passed_time":0.09110521489,"remaining_time":0.1207673779},
{"learn":[5.213524255],"iteration":43,"passed_time":0.09280570308,"remaining_time":0.1181163494},
{"learn":[5.189691584],"iteration":44,"passed_time":0.09410801861,"remaining_time":0.1150209116},
{"learn":[5.166052198],"iteration":45,"passed_time":0.09534826291,"remaining_time":0.1119305695},
{"learn":[5.140406659],"iteration":46,"passed_time":0.09826382671,"remaining_time":0.110808145},
{"learn":[5.118929684],"iteration":47,"passed_time":0.1013474248,"remaining_time":0.1097930436},
{"learn":[5.108792602],"iteration":48,"passed_time":0.1034098109,"remaining_time":0.1076306195},
{"learn":[5.098141225],"iteration":49,"passed_time":0.1043762753,"remaining_time":0.1043762753},
{"learn":[5.085926393],"iteration":50,"passed_time":0.1053480968,"remaining_time":0.1012167989},
{"learn":[5.067816804],"iteration":51,"passed_time":0.1063922177,"remaining_time":0.09820820093},
{"learn":[5.049834901],"iteration":52,"passed_time":0.1074154514,"remaining_time":0.09525521159},
{"learn":[5.03838627],"iteration":53,"passed_time":0.108393349,"remaining_time":0.09233507505},
{"learn":[5.033534248],"iteration":54,"passed_time":0.1089854811,"remaining_time":0.08916993911},
{"learn":[5.023726885],"iteration":55,"passed_time":0.109879364,"remaining_time":0.08633378598},
{"learn":[5.01290392],"iteration":56,"passed_time":0.1108768012,"remaining_time":0.08364390268},
{"learn":[5.005569127],"iteration":57,"passed_time":0.1118885905,"remaining_time":0.08102277246},
{"learn":[4.989969032],"iteration":58,"passed_time":0.1138044972,"remaining_time":0.07908448107},
{"learn":[4.976762446],"iteration":59,"passed_time":0.1154650959,"remaining_time":0.07697673063},
{"learn":[4.967222715],"iteration":60,"passed_time":0.1165392084,"remaining_time":0.07450867422},
{"learn":[4.954407599],"iteration":61,"passed_time":0.1175371415,"remaining_time":0.07203889315},
{"learn":[4.942125056],"iteration":62,"passed_time":0.118575315,"remaining_time":0.0696394707},
{"learn":[4.930230716],"iteration":63,"passed_time":0.1196393121,"remaining_time":0.06729711308},
{"learn":[4.921695642],"iteration":64,"passed_time":0.1206704372,"remaining_time":0.06497638925},
{"learn":[4.906405625],"iteration":65,"passed_time":0.1216298075,"remaining_time":0.06265777964},
{"learn":[4.894330248],"iteration":66,"passed_time":0.1226268514,"remaining_time":0.06039829992},
{"learn":[4.88211557],"iteration":67,"passed_time":0.1236579516,"remaining_time":0.05819197723},
{"learn":[4.877946398],"iteration":68,"passed_time":0.1247207364,"remaining_time":0.05603395405},
{"learn":[4.863182126],"iteration":69,"passed_time":0.1257343786,"remaining_time":0.05388616227},
{"learn":[4.84646533],"iteration":70,"passed_time":0.1267166098,"remaining_time":0.05175748849},
{"learn":[4.838014752],"iteration":71,"passed_time":0.1287995343,"remaining_time":0.05008870777},
{"learn":[4.82981137],"iteration":72,"passed_time":0.129821103,"remaining_time":0.0480160244},
{"learn":[4.817094767],"iteration":73,"passed_time":0.1308551589,"remaining_time":0.04597613692},
{"learn":[4.808314151],"iteration":74,"passed_time":0.1318470775,"remaining_time":0.04394902584},
{"learn":[4.796235023],"iteration":75,"passed_time":0.1328264609,"remaining_time":0.04194519819},
{"learn":[4.784434534],"iteration":76,"passed_time":0.1337716864,"remaining_time":0.03995777645},
{"learn":[4.774402487],"iteration":77,"passed_time":0.1347568444,"remaining_time":0.03800834072},
{"learn":[4.76731896],"iteration":78,"passed_time":0.1357286955,"remaining_time":0.03607977982},
{"learn":[4.75934113],"iteration":79,"passed_time":0.1367200575,"remaining_time":0.03418001438},
{"learn":[4.754106378],"iteration":80,"passed_time":0.137693656,"remaining_time":0.03229851189},
{"learn":[4.744002932],"iteration":81,"passed_time":0.1387499337,"remaining_time":0.03045730252},
{"learn":[4.731700554],"iteration":82,"passed_time":0.1397333732,"remaining_time":0.02862008848},
{"learn":[4.723284153],"iteration":83,"passed_time":0.1407461237,"remaining_time":0.02680878547},
{"learn":[4.712232782],"iteration":84,"passed_time":0.1417410331,"remaining_time":0.0250131235},
{"learn":[4.703046867],"iteration":85,"passed_time":0.1438727932,"remaining_time":0.02342115238},
{"learn":[4.698601855],"iteration":86,"passed_time":0.1449253508,"remaining_time":0.02165551218},
{"learn":[4.692429407],"iteration":87,"passed_time":0.1459464789,"remaining_time":0.01990179257},
{"learn":[4.675027364],"iteration":88,"passed_time":0.1470209016,"remaining_time":0.01817112267},
{"learn":[4.662368584],"iteration":89,"passed_time":0.1480580587,"remaining_time":0.01645089541},
{"learn":[4.646206172],"iteration":90,"passed_time":0.1490936964,"remaining_time":0.01474553042},
{"learn":[4.641245848],"iteration":91,"passed_time":0.1500450547,"remaining_time":0.01304739606},
{"learn":[4.633900435],"iteration":92,"passed_time":0.1510719326,"remaining_time":0.01137100568},
{"learn":[4.624738236],"iteration":93,"passed_time":0.1520741368,"remaining_time":0.009706859795},
{"learn":[4.612798287],"iteration":94,"passed_time":0.153009578,"remaining_time":0.008053135683},
{"learn":[4.605222001],"iteration":95,"passed_time":0.1539857219,"remaining_time":0.006416071744},
{"learn":[4.601725912],"iteration":96,"passed_time":0.1549396831,"remaining_time":0.004791948962},
{"learn":[4.59722371],"iteration":97,"passed_time":0.1560335791,"remaining_time":0.003184358758},
{"learn":[4.580235665],"iteration":98,"passed_time":0.1580648412,"remaining_time":0.001596614557},
{"learn":[4.57591791],"iteration":99,"passed_time":0.1590763946,"remaining_time":0}
]}